Metadata-Version: 2.1
Name: ctfcred
Version: 1.0.0
Summary: CTF Credential Manager
Home-page: https://github.com/qtc-de/ctfcred
Author: Tobias Neitzel (@qtc_de)
Author-email: 
License: UNKNOWN
Platform: UNKNOWN
Classifier: Programming Language :: Python :: 3
Classifier: Operating System :: Unix
Classifier: License :: OSI Approved :: GNU General Public License v3 (GPLv3)
